secuer/__init__.py
secuer/secuer.py
secuer/secuerconsensus.py
shangchuan/__init__.py
shangchuan/utils.py
shangchuan-2.1.dist-info/METADATA
shangchuan-2.1.dist-info/WHEEL
shangchuan-2.1.dist-info/entry_points.txt
shangchuan-2.1.dist-info/top_level.txt
shangchuan-2.1.dist-info/RECORD
