Metadata-Version: 2.1
Name: shangchuan
Version: 2.1
Summary: mHapTk is a tool kit for analysis of DNA methylation haplotypes. It has 5 sub-commands: tanghulu, stat, genomeWide, R2 and MHBDiscovery
Author: ckw
Author-email: 1353595807@qq.com
